jwrap.py
jwrap-0.3.dist-info/LICENSE
jwrap-0.3.dist-info/METADATA
jwrap-0.3.dist-info/WHEEL
jwrap-0.3.dist-info/top_level.txt
jwrap-0.3.dist-info/RECORD
