Metadata-Version: 2.1
Name: jwrap
Version: 0.3
Summary: Wrapper for easy interacting with JSON files.
Home-page: https://gitea.gch.icu/gd/jwrap/
Author: gd
Author-email: gechandev@gmail.com
License: UNKNOWN
Platform: UNKNOWN
Classifier: Programming Language :: Python :: 3.9
Classifier: License :: OSI Approved :: The Unlicense (Unlicense)
Classifier: Operating System :: OS Independent
Requires-Python: >=3.6
